joke_client_analysis/__init__.py
joke_client_analysis/__main__.py
joke_client_analysis-0.1.0.dist-info/METADATA
joke_client_analysis-0.1.0.dist-info/WHEEL
joke_client_analysis-0.1.0.dist-info/top_level.txt
joke_client_analysis-0.1.0.dist-info/RECORD
