Metadata-Version: 2.1
Name: joke_client_analysis
Version: 0.1.0
Summary: Быстрая статистика клиентов по возрасту и городу
Author-email: Pablo_3_16 <p.ergle@edu.centraluniversity.ru>
License: MIT
Requires-Python: >=3.12
Requires-Dist: pandas>=2.2.3
